comfykit/__init__.py
comfykit/executor.py
comfykit/logger.py
comfykit/comfyui/__init__.py
comfykit/comfyui/base_executor.py
comfykit/comfyui/http_executor.py
comfykit/comfyui/models.py
comfykit/comfyui/runninghub_client.py
comfykit/comfyui/runninghub_executor.py
comfykit/comfyui/websocket_executor.py
comfykit/comfyui/workflow_parser.py
comfykit/utils/__init__.py
comfykit/utils/config_util.py
comfykit/utils/dynamic_util.py
comfykit/utils/file_util.py
comfykit/utils/image_util.py
comfykit/utils/network_util.py
comfykit/utils/openapi_util.py
comfykit/utils/os_util.py
comfykit/utils/process_util.py
comfykit/utils/runninghub_util.py
comfykit/utils/workflow_source_util.py
workflows/t2i_by_local_flux.json
comfykit-0.1.12.dist-info/METADATA
comfykit-0.1.12.dist-info/WHEEL
comfykit-0.1.12.dist-info/licenses/LICENSE
comfykit-0.1.12.dist-info/RECORD
