Metadata-Version: 2.4
Name: comfykit
Version: 0.1.12
Summary: ComfyUI Python SDK for developers - Build AI generation into your app
Project-URL: Homepage, https://github.com/puke3615/ComfyKit
Project-URL: Repository, https://github.com/puke3615/ComfyKit
Project-URL: Issues, https://github.com/puke3615/ComfyKit/issues
Author-email: Fan Wu <1129090915@qq.com>
License: MIT
License-File: LICENSE
Keywords: AI,AIGC,API,ComfyUI,FLUX,Image Generation,RunningHub,SDK,Stable Diffusion
Classifier: Development Status :: 4 - Beta
Classifier: Intended Audience :: Developers
Classifier: License :: OSI Approved :: MIT License
Classifier: Operating System :: OS Independent
Classifier: Programming Language :: Python :: 3
Classifier: Programming Language :: Python :: 3 :: Only
Classifier: Programming Language :: Python :: 3.10
Classifier: Programming Language :: Python :: 3.11
Classifier: Programming Language :: Python :: 3.12
Classifier: Topic :: Multimedia :: Graphics
Classifier: Topic :: Scientific/Engineering :: Artificial Intelligence
Classifier: Topic :: Software Development :: Libraries :: Application Frameworks
Requires-Python: >=3.10
Requires-Dist: aiofiles>=23.0
Requires-Dist: aiohttp>=3.9.0
Requires-Dist: httpx>=0.25.0
Requires-Dist: pillow>=10.0
Requires-Dist: pydantic>=2.0
Requires-Dist: tomli>=2.0.0; python_version < '3.11'
Requires-Dist: websockets>=12.0
Provides-Extra: dev
Requires-Dist: black>=23.0; extra == 'dev'
Requires-Dist: pytest-asyncio>=0.21; extra == 'dev'
Requires-Dist: pytest>=7.0; extra == 'dev'
Requires-Dist: ruff>=0.1.0; extra == 'dev'
